[{"position": 1, "title": "VenturePact Information | VenturePact Profile - RocketReach", "link": "https://rocketreach.co/venturepact-profile_b5f764ccf42e8917", "displayed_link": "rocketreach.co \u203a venturepact-profile_b5f764ccf42e8917", "snippet": "VenturePact Revenue: $71.60 Million | Employees: 39 | Industry: Software, Software Development & Design, Android | View VenturePact's full company profile\u00a0...", "cached_page_link": "https://webcache.googleusercontent.com/search?q=cache:ZCTlna9Lg3kJ:https://rocketreach.co/venturepact-profile_b5f764ccf42e8917+&cd=1&hl=en&ct=clnk&gl=us"}]